yaml_update_last_modified_date/__init__.py
yaml_update_last_modified_date/__main__.py
yaml_update_last_modified_date/main.py
yaml_update_last_modified_date-1.1.1.dist-info/LICENSE
yaml_update_last_modified_date-1.1.1.dist-info/METADATA
yaml_update_last_modified_date-1.1.1.dist-info/WHEEL
yaml_update_last_modified_date-1.1.1.dist-info/entry_points.txt
yaml_update_last_modified_date-1.1.1.dist-info/RECORD
