Metadata-Version: 2.1
Name: yaml-update-last-modified-date
Version: 1.1.1
Summary: Set the last modified date in YAML front matter of edited markdown files.
License: Unlicense
Author: Francis T. O'Donovan
Author-email: proinsias@users.noreply.github.com
Requires-Python: >=3.8,<4.0
Classifier: License :: Other/Proprietary License
Classifier: Programming Language :: Python :: 3
Classifier: Programming Language :: Python :: 3.8
Classifier: Programming Language :: Python :: 3.9
Classifier: Programming Language :: Python :: 3.10
Classifier: Programming Language :: Python :: 3.11
Requires-Dist: GitPython (>=3.1.31,<4.0.0)
Requires-Dist: rich (>=13.3.4,<14.0.0)
Requires-Dist: typer (>=0.7.0,<0.8.0)
